tagging_module/__init__.py
tagging_module/tagging_service.py
tagging_module/tagging_system.py
tagging_module/config/rules.yml
tagging_module-0.0.8.dist-info/METADATA
tagging_module-0.0.8.dist-info/WHEEL
tagging_module-0.0.8.dist-info/top_level.txt
tagging_module-0.0.8.dist-info/RECORD
