Metadata-Version: 2.1
Name: tagging-module
Version: 0.0.8
Summary: A lightweight rule based tech content tagging module for Python
Author: aditya-xq
Author-email: adityavivek.xq@gmail.com
Requires-Dist: PyYAML
